lzbot/__init__.py
lzbot/api.py
lzbot/audio.py
lzbot/bot.py
lzbot/channel.py
lzbot/client.py
lzbot/config.py
lzbot/connection.py
lzbot/errors.py
lzbot/flags.py
lzbot/forum.py
lzbot/gateway.py
lzbot/guild.py
lzbot/http.py
lzbot/interaction.py
lzbot/json_read.py
lzbot/logging.py
lzbot/manage.py
lzbot/message.py
lzbot/reaction.py
lzbot/robot.py
lzbot/user.py
lzbot/ext/__init__.py
lzbot/ext/command_util.py
lzbot/ext/channel_jump/__init__.py
lzbot/ext/cog_apscheduler/__init__.py
lzbot/ext/cog_yaml/__init__.py
lzbot/ext/convert_color/__init__.py
lzbot/types/__init__.py
lzbot/types/announce.py
lzbot/types/audio.py
lzbot/types/channel.py
lzbot/types/emoji.py
lzbot/types/forum.py
lzbot/types/gateway.py
lzbot/types/guild.py
lzbot/types/inline.py
lzbot/types/interaction.py
lzbot/types/message.py
lzbot/types/permission.py
lzbot/types/pins_message.py
lzbot/types/reaction.py
lzbot/types/rich_text.py
lzbot/types/robot.py
lzbot/types/schedule.py
lzbot/types/session.py
lzbot/types/user.py
lzbot-1.1.dist-info/LICENSE
lzbot-1.1.dist-info/METADATA
lzbot-1.1.dist-info/WHEEL
lzbot-1.1.dist-info/top_level.txt
lzbot-1.1.dist-info/RECORD
